pingera/__init__.py
pingera/api_client.py
pingera/api_response.py
pingera/configuration.py
pingera/exceptions.py
pingera/py.typed
pingera/rest.py
pingera/api/__init__.py
pingera/api/alerts_api.py
pingera/api/auth_enhanced_api.py
pingera/api/check_groups_api.py
pingera/api/check_secrets_api.py
pingera/api/checks_api.py
pingera/api/checks_unified_results_api.py
pingera/api/execution_groups_api.py
pingera/api/heartbeats_api.py
pingera/api/o_auth_api.py
pingera/api/on_demand_checks_api.py
pingera/api/organizations_api.py
pingera/api/page_passwords_api.py
pingera/api/secrets_api.py
pingera/api/status_pages_api.py
pingera/api/status_pages_components_api.py
pingera/api/status_pages_incidents_api.py
pingera/api/usage_api.py
pingera/api/users_api.py
pingera/api/webauthn_api.py
pingera/models/__init__.py
pingera/models/alert.py
pingera/models/alert_channel.py
pingera/models/alert_channel1.py
pingera/models/alert_list.py
pingera/models/alert_notification.py
pingera/models/alert_rule.py
pingera/models/alert_rule1.py
pingera/models/alert_stats.py
pingera/models/api_token.py
pingera/models/auth_begin_request.py
pingera/models/auth_preferences.py
pingera/models/auth_preferences1.py
pingera/models/auth_recommendations.py
pingera/models/auth_setup_status.py
pingera/models/authentication_complete.py
pingera/models/authentication_complete_response.py
pingera/models/authentication_options_response.py
pingera/models/check_group.py
pingera/models/check_group1.py
pingera/models/check_group2.py
pingera/models/check_group_list.py
pingera/models/check_job.py
pingera/models/check_secret.py
pingera/models/check_secret_input.py
pingera/models/check_server.py
pingera/models/component.py
pingera/models/component1.py
pingera/models/component_uptime.py
pingera/models/component_uptime_bulk_request.py
pingera/models/component_uptime_events.py
pingera/models/credential.py
pingera/models/credential_update.py
pingera/models/credentials_list_response.py
pingera/models/enhanced_login.py
pingera_sdk-1.0.15.dist-info/licenses/LICENSE
pingera_sdk-1.0.15.dist-info/METADATA
pingera_sdk-1.0.15.dist-info/WHEEL
pingera_sdk-1.0.15.dist-info/top_level.txt
pingera_sdk-1.0.15.dist-info/RECORD
