Metadata-Version: 2.4
Name: pingera-sdk
Version: 1.0.15
Summary: Python SDK for the Pingera monitoring platform API
Home-page: https://github.com/pingera/pingera-sdk
Author: Pingera Team
Author-email: Pingera Team <privet@pingera.ru>
License: MIT
Project-URL: Homepage, https://pingera.ru
Project-URL: Documentation, https://docs.pingera.ru/api/overview
Project-URL: Repository, https://github.com/pingera/pingera-sdk
Project-URL: Bug Tracker, https://github.com/pingera/pingera-sdk/issues
Project-URL: API Documentation, https://api.pingera.ru
Keywords: pingera,monitoring,api,sdk,status-page,incidents,components
Classifier: Development Status :: 5 - Production/Stable
Classifier: Intended Audience :: Developers
Classifier: License :: OSI Approved :: MIT License
Classifier: Operating System :: OS Independent
Classifier: Programming Language :: Python :: 3
Classifier: Programming Language :: Python :: 3.8
Classifier: Programming Language :: Python :: 3.9
Classifier: Programming Language :: Python :: 3.10
Classifier: Programming Language :: Python :: 3.11
Classifier: Programming Language :: Python :: 3.12
Classifier: Topic :: Internet :: WWW/HTTP :: HTTP Servers
Classifier: Topic :: System :: Monitoring
Classifier: Topic :: System :: Networking :: Monitoring
Classifier: Topic :: Software Development :: Libraries :: Python Modules
Requires-Python: >=3.9
License-File: LICENSE
Requires-Dist: httpx>=0.24.0
Requires-Dist: pydantic>=2.0.0
Requires-Dist: pytest-cov>=4.0.0
Requires-Dist: pytest>=7.0.0
Requires-Dist: typing-extensions>=4.0.0
Requires-Dist: pytest-asyncio>=0.21.0
Requires-Dist: setuptools>=75.3.2
Requires-Dist: python-dateutil>=2.9.0.post0
Requires-Dist: urllib3>=2.2.3
Provides-Extra: dev
Requires-Dist: pytest>=7.0.0; extra == "dev"
Requires-Dist: pytest-cov>=4.0.0; extra == "dev"
Requires-Dist: pytest-asyncio>=0.21.0; extra == "dev"
Requires-Dist: black>=23.0.0; extra == "dev"
Requires-Dist: mypy>=1.0.0; extra == "dev"
Requires-Dist: pre-commit>=3.0.0; extra == "dev"
Requires-Dist: twine>=4.0.0; extra == "dev"
Provides-Extra: test
Requires-Dist: pytest>=7.0.0; extra == "test"
Requires-Dist: pytest-cov>=4.0.0; extra == "test"
Requires-Dist: pytest-asyncio>=0.21.0; extra == "test"
Dynamic: author
Dynamic: home-page
Dynamic: license-file
Dynamic: requires-python
